dnplot/__init__.py
dnplot/defaults.py
dnplot/draw_functions/__init__.py
dnplot/draw_functions/draw.py
dnplot/plot_functions/__init__.py
dnplot/plot_functions/dnora_functions.py
dnplot/plot_functions/plotly_functions.py
dnplot/plotters/__init__.py
dnplot/plotters/plotters.py
dnplot-0.1.0.dist-info/LICENSE
dnplot-0.1.0.dist-info/METADATA
dnplot-0.1.0.dist-info/WHEEL
dnplot-0.1.0.dist-info/top_level.txt
dnplot-0.1.0.dist-info/RECORD
