Metadata-Version: 2.1
Name: dnplot
Version: 0.1.0
Summary: Plotting of data imported by the DNORA package
Author-email: Konstantinos Christakos <konstantinosc@met.no>, Jan-Victor Björkqvist <janvb@met.no>, Dominykas Jasas <dominykas.jasas@stud.vilniustech.lt>
Project-URL: repository, http://github.com/bjorkqvi/dnplot
License-File: LICENSE
Requires-Dist: numpy
Requires-Dist: matplotlib
Requires-Dist: cartopy
Requires-Dist: pandas
Requires-Dist: plotly
Requires-Dist: dash
Requires-Dist: scipy
Requires-Dist: cmocean
Requires-Dist: scikit-learn
